pysparkly/__init__.py
pysparkly/extensions/__init__.py
pysparkly/extensions/dataframe.py
pysparkly/helpers_column.py
pysparkly/helpers_dataframe.py
pysparkly-0.1.1.dist-info/LICENSE
pysparkly-0.1.1.dist-info/WHEEL
pysparkly-0.1.1.dist-info/METADATA
pysparkly-0.1.1.dist-info/RECORD
