Metadata-Version: 2.1
Name: pysparkly
Version: 0.1.1
Summary: Pyspark useful functions and extensions
Author: ugo-quelhas
Author-email: ugo.quelhas@edu.devinci.fr
Requires-Python: >=3.6,<4.0
Classifier: Programming Language :: Python :: 3
Classifier: Programming Language :: Python :: 3.6
Classifier: Programming Language :: Python :: 3.7
Classifier: Programming Language :: Python :: 3.8
Classifier: Programming Language :: Python :: 3.9
Requires-Dist: py-deco (>=0.1.0,<0.2.0)
Requires-Dist: pyspark (>=3.0.1,<4.0.0)
